magicnet/__about__.py
magicnet/__init__.py
magicnet/batteries/__init__.py
magicnet/batteries/asyncio_network_manager.py
magicnet/batteries/encoders.py
magicnet/batteries/logging_node.py
magicnet/batteries/transport_managers.py
magicnet/batteries/middlewares/__init__.py
magicnet/batteries/middlewares/message_validation.py
magicnet/batteries/middlewares/zone_routing.py
magicnet/batteries/transports/__init__.py
magicnet/batteries/transports/single_app.py
magicnet/batteries/transports/socket_asyncio.py
magicnet/core/__init__.py
magicnet/core/connection.py
magicnet/core/datagram_processor.py
magicnet/core/errors.py
magicnet/core/handle_filter.py
magicnet/core/net_globals.py
magicnet/core/net_message.py
magicnet/core/network_manager.py
magicnet/core/protocol_encoder.py
magicnet/core/transport_handler.py
magicnet/core/transport_manager.py
magicnet/netobjects/__init__.py
magicnet/netobjects/network_field.py
magicnet/netobjects/network_object.py
magicnet/netobjects/network_object_manager.py
magicnet/netobjects/network_object_meta.py
magicnet/netobjects/network_object_registry.py
magicnet/protocol/__init__.py
magicnet/protocol/message_processors.py
magicnet/protocol/network_types.py
magicnet/protocol/processor_base.py
magicnet/protocol/protocol_globals.py
magicnet/protocol/processors/__init__.py
magicnet/protocol/processors/data.py
magicnet/protocol/processors/handshake.py
magicnet/protocol/processors/network_objects.py
magicnet/util/__init__.py
magicnet/util/messenger.py
magicnet/util/typechecking/__init__.py
magicnet/util/typechecking/dataclass_converter.py
magicnet/util/typechecking/field_signature.py
magicnet/util/typechecking/magicnet_typechecker.py
magicnet/util/typechecking/typehint_marshal.py
magicnet-0.0.7.dist-info/METADATA
magicnet-0.0.7.dist-info/WHEEL
magicnet-0.0.7.dist-info/licenses/LICENSE
magicnet-0.0.7.dist-info/RECORD
