Metadata-Version: 2.4
Name: magicnet
Version: 0.0.7
Summary: MagicNet is a modern and flexible networking library
Project-URL: homepage, https://github.com/wizzerinus/magicnet
Project-URL: bugtracker, https://github.com/wizzerinus/magicnet/issues
Author-email: Wizzerinus <quillinde@gmail.com>
License-Expression: MIT
License-File: LICENSE
Keywords: astron,networking
Classifier: Development Status :: 2 - Pre-Alpha
Classifier: License :: OSI Approved :: MIT License
Classifier: Operating System :: OS Independent
Classifier: Programming Language :: Python :: 3.10
Classifier: Topic :: Internet
Classifier: Topic :: Software Development :: Libraries :: Application Frameworks
Classifier: Typing :: Typed
Requires-Python: >=3.10
Requires-Dist: typing-extensions
Provides-Extra: standard
Requires-Dist: msgpack~=1.0; extra == 'standard'
